[
  {
    "id": "77c27cca-176b-4de0-b5a1-68a33584d1ca",
    "data": [
      {
        "text": "show details about phytate",
        "userDefined": false
      }
    ],
    "isTemplate": false,
    "count": 0,
    "updated": 1522271502
  },
  {
    "id": "4b5342e9-7dea-44cc-a306-6c96fa9e40ca",
    "data": [
      {
        "text": "what is phytate",
        "userDefined": false
      }
    ],
    "isTemplate": false,
    "count": 0,
    "updated": 1522271502
  },
  {
    "id": "bda05e70-a617-4b16-87fc-99f51f861326",
    "data": [
      {
        "text": "i want to know about phytate",
        "userDefined": false
      }
    ],
    "isTemplate": false,
    "count": 0,
    "updated": 1522271502
  },
  {
    "id": "099482f9-f32e-466f-96cc-2106b9657b61",
    "data": [
      {
        "text": "tell me about phytate",
        "userDefined": false
      }
    ],
    "isTemplate": false,
    "count": 0,
    "updated": 1522271502
  }
]